tpds_extension/fw_validation/extension.yaml
tpds_extension/fw_validation/setup.py
tpds_extension/fw_validation/version.py
tpds_extension/fw_validation/TrustFlex/Firmware Validation.ipynb
tpds_extension/fw_validation/TrustFlex/example_app.hex
tpds_extension/fw_validation/TrustFlex/example_boot.hex
tpds_extension/fw_validation/TrustFlex/firmware.zip
tpds_extension/fw_validation/TrustFlex/assets/Firmware Validation.md
tpds_extension/fw_validation/TrustFlex/assets/images/Firmware validation.png
tpds_extension/fw_validation/TrustFlex/assets/images/c-snippet.PNG
tpds_extension/fw_validation/TrustFlex/assets/images/crypto-assets.png
tpds_extension/fw_validation/TrustFlex/assets/images/td_firmware_validation.png
tpds_extension/fw_validation/TrustFlex/assets/images/usecase_steps.png
tpds_extension/fw_validation/TrustFlex/assets/python/firmware_validation.py
tpds_extension_spg_fw_validation-2.2.4.dist-info/METADATA
tpds_extension_spg_fw_validation-2.2.4.dist-info/WHEEL
tpds_extension_spg_fw_validation-2.2.4.dist-info/top_level.txt
tpds_extension_spg_fw_validation-2.2.4.dist-info/RECORD
